formula1py/__init__.py
formula1py/formula1.py
formula1py/tests/__init__.py
formula1py/tests/test.py
formula1py-0.10.0.dist-info/LICENSE
formula1py-0.10.0.dist-info/WHEEL
formula1py-0.10.0.dist-info/METADATA
formula1py-0.10.0.dist-info/RECORD
