Metadata-Version: 2.1
Name: formula1py
Version: 0.10.0
Summary: Python package that wraps Ergast F1 API
Home-page: https://github.com/alexraskin/f1py
Author: Alex Raskin
Author-email: alexraskin@fastmail.fm
Requires-Python: >=3.7
Classifier: License :: OSI Approved :: MIT License
Requires-Dist: requests >=2.20
